.gitlab-ci.yml
.travis.yml
CHANGES.rst
CONTRIBUTORS.rst
DEVELOP.rst
LICENSE.GPL
LICENSE.rst
MANIFEST.in
README.rst
requirements.txt
setup.cfg
setup.py
docs/index.rst
src/collective/__init__.py
src/collective.behavior.gallery.egg-info/PKG-INFO
src/collective.behavior.gallery.egg-info/SOURCES.txt
src/collective.behavior.gallery.egg-info/dependency_links.txt
src/collective.behavior.gallery.egg-info/entry_points.txt
src/collective.behavior.gallery.egg-info/namespace_packages.txt
src/collective.behavior.gallery.egg-info/not-zip-safe
src/collective.behavior.gallery.egg-info/requires.txt
src/collective.behavior.gallery.egg-info/top_level.txt
src/collective/behavior/__init__.py
src/collective/behavior/gallery/__init__.py
src/collective/behavior/gallery/configure.zcml
src/collective/behavior/gallery/interfaces.py
src/collective/behavior/gallery/permissions.zcml
src/collective/behavior/gallery/setuphandlers.py
src/collective/behavior/gallery/testing.py
src/collective/behavior/gallery/upgrades.py
src/collective/behavior/gallery/upgrades.zcml
src/collective/behavior/gallery/behaviors/__init__.py
src/collective/behavior/gallery/behaviors/configure.zcml
src/collective/behavior/gallery/behaviors/folderish_gallery.py
src/collective/behavior/gallery/browser/__init__.py
src/collective/behavior/gallery/browser/configure.zcml
src/collective/behavior/gallery/browser/custom_view.pt
src/collective/behavior/gallery/browser/files.pt
src/collective/behavior/gallery/browser/folder_view.pt
src/collective/behavior/gallery/browser/folder_view.py
src/collective/behavior/gallery/browser/gallery.pt
src/collective/behavior/gallery/browser/viewlet.py
src/collective/behavior/gallery/browser/overrides/.gitkeep
src/collective/behavior/gallery/browser/static/gallery.css
src/collective/behavior/gallery/browser/static/gallery.min.css
src/collective/behavior/gallery/browser/static/gallery.min.css.map
src/collective/behavior/gallery/browser/static/gallery.min.js
src/collective/behavior/gallery/browser/static/gallery.min.js.map
src/collective/behavior/gallery/browser/static/jquery-fancybox-compiled.js
src/collective/behavior/gallery/browser/static/jquery.fancybox.css
src/collective/behavior/gallery/browser/static/jquery.fancybox.js
src/collective/behavior/gallery/locales/collective.behavior.gallery.pot
src/collective/behavior/gallery/locales/update.sh
src/collective/behavior/gallery/locales/fr/LC_MESSAGES/collective.behavior.gallery.po
