Metadata-Version: 1.1
Name: collective.behavior.gallery
Version: 1.0a6
Summary: Add a gallery of images to Folderish content types
Home-page: https://pypi.python.org/pypi/collective.behavior.gallery
Author: Nicolas Demonte
Author-email: support@lists.affinitic.be
License: GPL version 2
Keywords: Python Plone
Platform: UNKNOWN
Classifier: Environment :: Web Environment
Classifier: Framework :: Plone
Classifier: Framework :: Plone :: 5.0
Classifier: Framework :: Plone :: 5.1
Classifier: Programming Language :: Python
Classifier: Programming Language :: Python :: 2.7
Classifier: Operating System :: OS Independent
Classifier: License :: OSI Approved :: GNU General Public License v2 (GPLv2)
